{
    "fluentMethods": true,
    "relationships": [
        {
            "relationshipName": "freeClassRecord",
            "otherEntityName": "freeClassRecord",
            "relationshipType": "many-to-many",
            "ownerSide": false,
            "otherEntityRelationshipName": "classCategory"
        }
    ],
    "fields": [
        {
            "fieldName": "name",
            "fieldType": "String"
        },
        {
            "fieldName": "code",
            "fieldType": "String"
        },
        {
            "fieldName": "description",
            "fieldType": "String"
        }
    ],
    "changelogDate": "20180414114141",
    "dto": "no",
    "service": "no",
    "entityTableName": "class_category",
    "jpaMetamodelFiltering": false,
    "pagination": "pagination"
}
